nota/__init__.py
nota/__main__.py
nota/main.py
nota/notaclass.py
nota-0.8.11.dist-info/LICENSE
nota-0.8.11.dist-info/METADATA
nota-0.8.11.dist-info/WHEEL
nota-0.8.11.dist-info/entry_points.txt
nota-0.8.11.dist-info/top_level.txt
nota-0.8.11.dist-info/zip-safe
nota-0.8.11.dist-info/RECORD
