Metadata-Version: 2.1
Name: nota
Version: 0.8.11
Summary: Text-based note taker
Home-page: https://github.com/dankelley/nota
Author: Dan Kelley
Author-email: kelley.dan@gmail.com
License: GPL3
Platform: UNKNOWN
Classifier: Development Status :: 3 - Alpha
Classifier: Environment :: Console
Classifier: Topic :: Utilities
Classifier: License :: OSI Approved :: GNU General Public License v3 (GPLv3)
Requires-Python: >=3.6
License-File: LICENSE
